classes/__init__.py
classes/googlesearch.py
classes/openai.py
classes/proxycurl.py
lib/__init__.py
lib/functions.py
linkedframe/__init__.py
linkedframe/enrichment.py
processor/__init__.py
tests/__init__.py
tests/test_enrichment.py
linkedframe-1.0.4.dist-info/METADATA
linkedframe-1.0.4.dist-info/WHEEL
linkedframe-1.0.4.dist-info/top_level.txt
linkedframe-1.0.4.dist-info/RECORD
